{
  "members_title": "投手",
  "members_data": [
    {
      "members_name": "林詩翔",
      "members_number": "5",
      "members_pos": "投手",
      "members_votinghabits": "右投左打",
      "members_height": "181 CM",
      "members_weight": "83 KG",
      "members_birthday": "2001/07/31",
      "members_first_appearance": "2024/05/22",
      "members_educational_background": "大同學院",
      "members_image": "player_a_5",
      "members_url": "https://www.cpbl.com.tw/team/person?acnt=0000006949"
    },
    {
      "members_name": "謝葆錡",
      "members_number": "10",
      "members_pos": "投手",
      "members_votinghabits": "右投左打",
      "members_height": "184 CM",
      "members_weight": "93 KG",
      "members_birthday": "1999/09/10",
      "members_first_appearance": "2024/04/04",
      "members_educational_background": "國立體大",
      "members_image": "player_a_10",
      "members_url": "https://www.cpbl.com.tw/team/person?acnt=0000006917"
    },
    {
      "members_name": "陳宇宏",
      "members_number": "17",
      "members_pos": "投手",
      "members_votinghabits": "右投右打",
      "members_height": "180 CM",
      "members_weight": "73 KG",
      "members_birthday": "2001/05/12",
      "members_first_appearance": "2024/04/06",
      "members_educational_background": "台鋼科大",
      "members_image": "player_a_17",
      "members_url": "https://www.cpbl.com.tw/team/person?Acnt=0000006833"
    },
    {
      "members_name": "吉田一将",
      "members_number": "41",
      "members_pos": "投手",
      "members_votinghabits": "右投左打",
      "members_height": "191 CM",
      "members_weight": "96 KG",
      "members_birthday": "1989/09/24",
      "members_first_appearance": "2024/08/25",
      "members_educational_background": "",
      "members_image": "player_a_17",
      "members_url": "https://www.cpbl.com.tw/team/person?Acnt=0000007274"
    },
    {
      "members_name": "黃群",
      "members_number": "46",
      "members_pos": "投手",
      "members_votinghabits": "左投左打",
      "members_height": "176 CM",
      "members_weight": "81 KG",
      "members_birthday": "2003/03/184",
      "members_first_appearance": "2024/04/06",
      "members_educational_background": "南華大學",
      "members_image": "player_a_46",
      "members_url": "https://www.cpbl.com.tw/team/person?Acnt=0000006982"
    },
    {
      "members_name": "伍祐城",
      "members_number": "55",
      "members_pos": "投手",
      "members_votinghabits": "右投左打",
      "members_height": "180 CM",
      "members_weight": "90 KG",
      "members_birthday": "2004/02/15",
      "members_first_appearance": "2024/04/07",
      "members_educational_background": "平鎮高中",
      "members_image": "player_a_55",
      "members_url": "https://www.cpbl.com.tw/team/person?Acnt=0000006921"
    },
    {
      "members_name": "陳暐皓",
      "members_number": "58",
      "members_pos": "投手",
      "members_votinghabits": "右投右打",
      "members_height": "177 CM",
      "members_weight": "79 KG",
      "members_birthday": "1999/09/24",
      "members_first_appearance": "2024/04/30",
      "members_educational_background": "國立體大",
      "members_image": "player_a_58",
      "members_url": "https://www.cpbl.com.tw/team/person?Acnt=0000006750"
    },
    {
      "members_name": "陳柏清",
      "members_number": "66",
      "members_pos": "投手",
      "members_votinghabits": "左投左打",
      "members_height": "182 CM",
      "members_weight": "98 KG",
      "members_birthday": "1998/10/25",
      "members_first_appearance": "2024/04/06",
      "members_educational_background": "南華大學",
      "members_image": "player_a_66",
      "members_url": "https://www.cpbl.com.tw/team/person?Acnt=0000006832"
    },
    {
      "members_name": "許育銘",
      "members_number": "74",
      "members_pos": "投手",
      "members_votinghabits": "左投左打",
      "members_height": "180 CM",
      "members_weight": "82 KG",
      "members_birthday": "1998/09/25",
      "members_first_appearance": "2024/04/13",
      "members_educational_background": "臺北市大",
      "members_image": "player_a_74",
      "members_url": "https://www.cpbl.com.tw/team/person?Acnt=0000006767"
    },
    {
      "members_name": "許峻暘",
      "members_number": "84",
      "members_pos": "投手",
      "members_votinghabits": "右投左打",
      "members_height": "181 CM",
      "members_weight": "73 KG",
      "members_birthday": "1998/03/23",
      "members_first_appearance": "2021/10/13",
      "members_educational_background": "開南大學",
      "members_image": "player_a_84",
      "members_url": "https://www.cpbl.com.tw/team/person?Acnt=0000005285"
    },
    {
      "members_name": "巫柏葳",
      "members_number": "92",
      "members_pos": "投手",
      "members_votinghabits": "右投左打",
      "members_height": "183 CM",
      "members_weight": "80 KG",
      "members_birthday": "2002/10/02",
      "members_first_appearance": "2024/05/22",
      "members_educational_background": "崑山科大",
      "members_image": "player_a_92",
      "members_url": "https://www.cpbl.com.tw/team/person?Acnt=0000007066"
    },
    {
      "members_name": "郭俞延",
      "members_number": "98",
      "members_pos": "投手",
      "members_votinghabits": "右投右打",
      "members_height": "185 CM",
      "members_weight": "85 KG",
      "members_birthday": "2003/09/08",
      "members_first_appearance": "2024/04/17",
      "members_educational_background": "台鋼科大",
      "members_image": "player_a_98",
      "members_url": "https://www.cpbl.com.tw/team/person?Acnt=0000007068"
    },
  ]
}
